typing_runtime/__init__.py
typing_runtime-0.0.0.dist-info/METADATA
typing_runtime-0.0.0.dist-info/WHEEL
typing_runtime-0.0.0.dist-info/top_level.txt
typing_runtime-0.0.0.dist-info/RECORD
