Metadata-Version: 2.4
Name: typing-runtime
Version: 0.0.0
Summary: WIP; beta to be published soon.
Requires-Python: >=3.15
Dynamic: requires-python
Dynamic: summary
